pytorch_icem/__init__.py
pytorch_icem/icem.py
pytorch_icem-0.1.0.dist-info/LICENSE.txt
pytorch_icem-0.1.0.dist-info/METADATA
pytorch_icem-0.1.0.dist-info/WHEEL
pytorch_icem-0.1.0.dist-info/top_level.txt
pytorch_icem-0.1.0.dist-info/RECORD
