Metadata-Version: 2.1
Name: pytorch-icem
Version: 0.1.0
Summary: Improved Cross Entropy Method (iCEM) implemented in pytorch
Author-email: Sheng Zhong <zhsh@umich.edu>, Thomas Power <tpower@umich.edu>
Maintainer-email: Sheng Zhong <zhsh@umich.edu>, Thomas Power <tpower@umich.edu>
License: Copyright (c) 2023 University of Michigan ARM Lab
Project-URL: Homepage, https://github.com/UM-ARM-Lab/pytorch_icem
Project-URL: Bug Reports, https://github.com/UM-ARM-Lab/pytorch_icem/issues
Project-URL: Source, https://github.com/UM-ARM-Lab/pytorch_icem
Keywords: icem,mpc,pytorch,control,robotics
Classifier: Development Status :: 4 - Beta
Classifier: Intended Audience :: Developers
Classifier: License :: OSI Approved :: MIT License
Classifier: Programming Language :: Python :: 3
Classifier: Programming Language :: Python :: 3 :: Only
Requires-Python: >=3.6
License-File: LICENSE.txt
Requires-Dist: torch
Requires-Dist: numpy
Requires-Dist: colorednoise
Requires-Dist: arm-pytorch-utilities >=0.4
Provides-Extra: test
Requires-Dist: pytest ; extra == 'test'
Requires-Dist: gym ; extra == 'test'
Requires-Dist: pygame ; extra == 'test'
Requires-Dist: pyglet ==1.5.27 ; extra == 'test'
Requires-Dist: window-recorder ; extra == 'test'
